{"__symbolic":"module","version":1,"metadata":{"SizeView":{"__symbolic":"class","decorators":[{"__symbolic":"call","expression":{"__symbolic":"reference","module":"@angular/core","name":"Component"},"arguments":[{"selector":"size-view","templateUrl":"sizeView.html"}]}],"members":{"entity":[{"__symbolic":"property","decorators":[{"__symbolic":"call","expression":{"__symbolic":"reference","module":"@angular/core","name":"Input"}}]}],"__ctor__":[{"__symbolic":"constructor","parameters":[{"__symbolic":"reference","module":"ionic-angular","name":"NavController"},{"__symbolic":"reference","module":"ionic-angular","name":"NavParams"},{"__symbolic":"reference","module":"ionic-angular","name":"AlertController"},{"__symbolic":"reference","module":"ng2-translate","name":"TranslateService"},{"__symbolic":"reference","module":"../../../db/component","name":"WhatsSizeDatabase"},{"__symbolic":"reference","module":"../../../providers/size","name":"SizeProvider"},{"__symbolic":"reference","module":"../../../providers/page","name":"PageProvider"},{"__symbolic":"reference","module":"../../../providers/ga","name":"GoogleAnalyticsProvider"}]}],"initialize":[{"__symbolic":"method"}],"loadModel":[{"__symbolic":"method"}],"getConvertedSizes":[{"__symbolic":"method"}],"editSize":[{"__symbolic":"method"}]}}}}